README.md
setup.py
gpt4all_j.egg-info/PKG-INFO
gpt4all_j.egg-info/SOURCES.txt
gpt4all_j.egg-info/dependency_links.txt
gpt4all_j.egg-info/not-zip-safe
gpt4all_j.egg-info/requires.txt
gpt4all_j.egg-info/top_level.txt
gpt4allj/__init__.py
gpt4allj/langchain.py
gpt4allj/lib.py
gpt4allj/model.py
gpt4allj/lib/avx/ggml.dll
gpt4allj/lib/avx/gptj.dll
gpt4allj/lib/avx/libggml.dylib
gpt4allj/lib/avx/libggml.so
gpt4allj/lib/avx/libgptj.dylib
gpt4allj/lib/avx/libgptj.so
gpt4allj/lib/avx2/ggml.dll
gpt4allj/lib/avx2/gptj.dll
gpt4allj/lib/avx2/libggml.dylib
gpt4allj/lib/avx2/libggml.so
gpt4allj/lib/avx2/libgptj.dylib
gpt4allj/lib/avx2/libgptj.so
gpt4allj/lib/basic/ggml.dll
gpt4allj/lib/basic/gptj.dll
gpt4allj/lib/basic/libggml.dylib
gpt4allj/lib/basic/libggml.so
gpt4allj/lib/basic/libgptj.dylib
gpt4allj/lib/basic/libgptj.so