Metadata-Version: 2.1
Name: gpt4all-j
Version: 0.2.6
Summary: Python bindings for the C++ port of GPT4All-J model.
Home-page: https://github.com/marella/gpt4all-j
Author: Ravindra Marella
Author-email: mv.ravindra007@gmail.com
License: MIT
Keywords: gpt4all-j gpt4all gpt-j ai llm cpp
Platform: UNKNOWN
Classifier: Development Status :: 1 - Planning
Classifier: Intended Audience :: Developers
Classifier: Intended Audience :: Education
Classifier: Intended Audience :: Science/Research
Classifier: License :: OSI Approved :: MIT License
Classifier: Programming Language :: Python :: 3
Classifier: Topic :: Scientific/Engineering
Classifier: Topic :: Scientific/Engineering :: Mathematics
Classifier: Topic :: Scientific/Engineering :: Artificial Intelligence
Classifier: Topic :: Software Development
Classifier: Topic :: Software Development :: Libraries
Classifier: Topic :: Software Development :: Libraries :: Python Modules
Provides-Extra: tests
